xlay/__init__.py
xlay/assembly.py
xlay/canvas.py
xlay/layout.py
xlay/pose.py
xlay/primitives.py
xlay-0.0.1.dist-info/METADATA
xlay-0.0.1.dist-info/WHEEL
xlay-0.0.1.dist-info/top_level.txt
xlay-0.0.1.dist-info/RECORD
